pyravendb/__init__.py
pyravendb/changes/__init__.py
pyravendb/changes/database_changes.py
pyravendb/changes/observers.py
pyravendb/commands/__init__.py
pyravendb/commands/commands_data.py
pyravendb/commands/raven_commands.py
pyravendb/connection/__init__.py
pyravendb/connection/cluster_requests_executor.py
pyravendb/connection/requests_executor.py
pyravendb/connection/requests_helpers.py
pyravendb/custom_exceptions/__init__.py
pyravendb/custom_exceptions/exceptions.py
pyravendb/data/__init__.py
pyravendb/data/certificate.py
pyravendb/data/counters.py
pyravendb/data/document_conventions.py
pyravendb/data/indexes.py
pyravendb/data/operation.py
pyravendb/data/patches.py
pyravendb/data/query.py
pyravendb/data/timeseries.py
pyravendb/hilo/__init__.py
pyravendb/hilo/hilo_generator.py
pyravendb/raven_operations/__init__.py
pyravendb/raven_operations/counters_operations.py
pyravendb/raven_operations/maintenance_operations.py
pyravendb/raven_operations/operations.py
pyravendb/raven_operations/query_operation.py
pyravendb/raven_operations/server_operations.py
pyravendb/raven_operations/timeseries_operations.py
pyravendb/store/__init__.py
pyravendb/store/document_session.py
pyravendb/store/document_store.py
pyravendb/store/session_counters.py
pyravendb/store/session_query.py
pyravendb/store/session_timeseries.py
pyravendb/store/stream.py
pyravendb/subscriptions/__init__.py
pyravendb/subscriptions/data.py
pyravendb/subscriptions/document_subscriptions.py
pyravendb/subscriptions/subscription.py
pyravendb/tests/__init__.py
pyravendb/tests/test_base.py
pyravendb/tests/database_changes/__init__.py
pyravendb/tests/database_changes/test_database_changes.py
pyravendb/tests/operations_tests/__init__.py
pyravendb/tests/operations_tests/test_counters_operations.py
pyravendb/tests/operations_tests/test_maintenance_operations.py
pyravendb/tests/operations_tests/test_operations.py
pyravendb/tests/operations_tests/test_server_operations.py
pyravendb-5.0.0.5.dist-info/LICENSE
pyravendb-5.0.0.5.dist-info/METADATA
pyravendb-5.0.0.5.dist-info/WHEEL
pyravendb-5.0.0.5.dist-info/top_level.txt
pyravendb-5.0.0.5.dist-info/RECORD
