Metadata-Version: 2.1
Name: pyravendb
Version: 5.0.0.5
Summary: Official python client for RavenDB NoSQL Document Database
Home-page: https://github.com/ravendb/RavenDB-Python-Client
Author: RavenDB
Author-email: support@ravendb.net
License: MIT
Keywords: pyravendb
Platform: UNKNOWN
Requires-Python: ~=3.5
License-File: LICENSE
